{"Siri":{"ServiceDelivery":{"ResponseTimestamp":"2014-11-19T17:23:26.316-05:00","StopMonitoringDelivery":[{"MonitoredStopVisit":[{"MonitoredVehicleJourney":{"LineRef":"MTA NYCT_B45","DirectionRef":"1","FramedVehicleJourneyRef":{"DataFrameRef":"2014-11-19","DatedVehicleJourneyRef":"MTA NYCT_EN_D4-Weekday-SDon-102200_B65_110"},"JourneyPatternRef":"MTA_B450028","PublishedLineName":"B45","OperatorRef":"MTA NYCT","OriginRef":"MTA_303557","DestinationRef":"MTA_801026","DestinationName":"DNTWN BKLYN COURT ST","SituationRef":[{"SituationSimpleRef":"MTA NYCT_76244"}],"Monitored":true,"VehicleLocation":{"Longitude":-73.96337,"Latitude":40.675753},"Bearing":101.35462,"ProgressRate":"normalProgress","BlockRef":"MTA NYCT_EN_D4-Weekday-SDon_E_EN_27060_B84-204","VehicleRef":"MTA NYCT_6816","MonitoredCall":{"Extensions":{"Distances":{"PresentableDistance":"1 stop away","DistanceFromCall":345.93,"StopsFromCall":1,"CallDistanceAlongRoute":3984.23}},"StopPointRef":"MTA_303574","VisitNumber":1,"StopPointName":"WASHINGTON AV/BERGEN ST"},"OnwardCalls":{"OnwardCall":[{"Extensions":{"Distances":{"PresentableDistance":"approaching","DistanceFromCall":127.73,"StopsFromCall":0,"CallDistanceAlongRoute":3766.03}},"StopPointRef":"MTA_303573","VisitNumber":1,"StopPointName":"WASHINGTON AV/PROSPECT PL"},{"Extensions":{"Distances":{"PresentableDistance":"1 stop away","DistanceFromCall":345.93,"StopsFromCall":1,"CallDistanceAlongRoute":3984.23}},"StopPointRef":"MTA_303574","VisitNumber":1,"StopPointName":"WASHINGTON AV/BERGEN ST"},{"Extensions":{"Distances":{"PresentableDistance":"2 stops away","DistanceFromCall":533.56,"StopsFromCall":2,"CallDistanceAlongRoute":4171.86}},"StopPointRef":"MTA_303575","VisitNumber":1,"StopPointName":"WASHINGTON AV/PACIFIC ST"},{"Extensions":{"Distances":{"PresentableDistance":"3 stops away","DistanceFromCall":649.32,"StopsFromCall":3,"CallDistanceAlongRoute":4287.63}},"StopPointRef":"MTA_306514","VisitNumber":1,"StopPointName":"ATLANTIC AV/WASHINGTON AV"},{"Extensions":{"Distances":{"PresentableDistance":"4 stops away","DistanceFromCall":748.53,"StopsFromCall":4,"CallDistanceAlongRoute":4386.84}},"StopPointRef":"MTA_303576","VisitNumber":1,"StopPointName":"ATLANTIC AV/WAVERLY AV"},{"Extensions":{"Distances":{"PresentableDistance":"0.6 miles away","DistanceFromCall":933.06,"StopsFromCall":5,"CallDistanceAlongRoute":4571.36}},"StopPointRef":"MTA_303577","VisitNumber":1,"StopPointName":"ATLANTIC AV/VANDERBILT AV"},{"Extensions":{"Distances":{"PresentableDistance":"0.7 miles away","DistanceFromCall":1206.65,"StopsFromCall":6,"CallDistanceAlongRoute":4844.95}},"StopPointRef":"MTA_303578","VisitNumber":1,"StopPointName":"ATLANTIC AV/CARLTON AV"},{"Extensions":{"Distances":{"PresentableDistance":"0.8 miles away","DistanceFromCall":1296.08,"StopsFromCall":7,"CallDistanceAlongRoute":4934.38}},"StopPointRef":"MTA_801175","VisitNumber":1,"StopPointName":"ATLANTIC AV/CUMBERLAND ST"},{"Extensions":{"Distances":{"PresentableDistance":"1.1 miles away","DistanceFromCall":1847.65,"StopsFromCall":8,"CallDistanceAlongRoute":5485.95}},"StopPointRef":"MTA_303254","VisitNumber":1,"StopPointName":"FLATBUSH AV/ATLANTIC AV"},{"Extensions":{"Distances":{"PresentableDistance":"1.4 miles away","DistanceFromCall":2318.03,"StopsFromCall":9,"CallDistanceAlongRoute":5956.33}},"StopPointRef":"MTA_303256","VisitNumber":1,"StopPointName":"LIVINGSTON ST/NEVINS ST"},{"Extensions":{"Distances":{"PresentableDistance":"1.6 miles away","DistanceFromCall":2576.02,"StopsFromCall":10,"CallDistanceAlongRoute":6214.32}},"StopPointRef":"MTA_306892","VisitNumber":1,"StopPointName":"LIVINGSTON ST/BOND ST"},{"Extensions":{"Distances":{"PresentableDistance":"1.7 miles away","DistanceFromCall":2775.61,"StopsFromCall":11,"CallDistanceAlongRoute":6413.91}},"StopPointRef":"MTA_303258","VisitNumber":1,"StopPointName":"LIVINGSTON ST/HOYT ST"},{"Extensions":{"Distances":{"PresentableDistance":"1.8 miles away","DistanceFromCall":2928.64,"StopsFromCall":12,"CallDistanceAlongRoute":6566.94}},"StopPointRef":"MTA_303259","VisitNumber":1,"StopPointName":"LIVINGSTON ST/SMITH ST"},{"Extensions":{"Distances":{"PresentableDistance":"2.1 miles away","DistanceFromCall":3352.53,"StopsFromCall":13,"CallDistanceAlongRoute":6990.83}},"StopPointRef":"MTA_302434","VisitNumber":1,"StopPointName":"JORALEMON ST/COURT ST"},{"Extensions":{"Distances":{"PresentableDistance":"2.2 miles away","DistanceFromCall":3516.33,"StopsFromCall":14,"CallDistanceAlongRoute":7154.63}},"StopPointRef":"MTA_801026","VisitNumber":1,"StopPointName":"LIVINGSTON ST/COURT ST"}]}},"RecordedAtTime":"2014-11-19T17:23:18.000-05:00"},{"MonitoredVehicleJourney":{"LineRef":"MTA NYCT_B45","DirectionRef":"1","FramedVehicleJourneyRef":{"DataFrameRef":"2014-11-19","DatedVehicleJourneyRef":"MTA NYCT_EN_D4-Weekday-SDon-104200_B45_16"},"JourneyPatternRef":"MTA_B450028","PublishedLineName":"B45","OperatorRef":"MTA NYCT","OriginRef":"MTA_303557","DestinationRef":"MTA_801026","DestinationName":"DNTWN BKLYN COURT ST","OriginAimedDepartureTime":"2014-11-19T17:22:00.000-05:00","SituationRef":[{"SituationSimpleRef":"MTA NYCT_76244"}],"Monitored":true,"VehicleLocation":{"Longitude":-73.925231,"Latitude":40.672207},"Bearing":84.683975,"ProgressRate":"normalProgress","ProgressStatus":"prevTrip","BlockRef":"MTA NYCT_EN_D4-Weekday-SDon_E_EN_47520_B65-113","VehicleRef":"MTA NYCT_6820","MonitoredCall":{"Extensions":{"Distances":{"PresentableDistance":"3.0 miles away","DistanceFromCall":4865.83,"StopsFromCall":22,"CallDistanceAlongRoute":3984.23}},"StopPointRef":"MTA_303574","VisitNumber":1,"StopPointName":"WASHINGTON AV/BERGEN ST"},"OnwardCalls":{"OnwardCall":[{"Extensions":{"Distances":{"PresentableDistance":"0.5 miles away","DistanceFromCall":881.8,"StopsFromCall":0,"CallDistanceAlongRoute":0.2}},"StopPointRef":"MTA_303557","VisitNumber":1,"StopPointName":"ST JOHNS PL/RALPH AV"},{"Extensions":{"Distances":{"PresentableDistance":"0.7 miles away","DistanceFromCall":1115.38,"StopsFromCall":1,"CallDistanceAlongRoute":233.78}},"StopPointRef":"MTA_303558","VisitNumber":1,"StopPointName":"ST JOHNS PL/BUFFALO AV"},{"Extensions":{"Distances":{"PresentableDistance":"0.8 miles away","DistanceFromCall":1335.32,"StopsFromCall":2,"CallDistanceAlongRoute":453.72}},"StopPointRef":"MTA_306894","VisitNumber":1,"StopPointName":"ST JOHNS PL/ROCHESTER AV"},{"Extensions":{"Distances":{"PresentableDistance":"0.9 miles away","DistanceFromCall":1523.11,"StopsFromCall":3,"CallDistanceAlongRoute":641.51}},"StopPointRef":"MTA_303560","VisitNumber":1,"StopPointName":"ST JOHNS PL/UTICA AV"},{"Extensions":{"Distances":{"PresentableDistance":"1.1 miles away","DistanceFromCall":1802.45,"StopsFromCall":4,"CallDistanceAlongRoute":920.85}},"StopPointRef":"MTA_303561","VisitNumber":1,"StopPointName":"ST JOHNS PL/SCHENECTADY AV"},{"Extensions":{"Distances":{"PresentableDistance":"1.3 miles away","DistanceFromCall":2036.67,"StopsFromCall":5,"CallDistanceAlongRoute":1155.07}},"StopPointRef":"MTA_303562","VisitNumber":1,"StopPointName":"ST JOHNS PL/TROY AV"},{"Extensions":{"Distances":{"PresentableDistance":"1.4 miles away","DistanceFromCall":2270.79,"StopsFromCall":6,"CallDistanceAlongRoute":1389.19}},"StopPointRef":"MTA_303563","VisitNumber":1,"StopPointName":"ST JOHNS PL/ALBANY AV"},{"Extensions":{"Distances":{"PresentableDistance":"1.5 miles away","DistanceFromCall":2458.65,"StopsFromCall":7,"CallDistanceAlongRoute":1577.05}},"StopPointRef":"MTA_303564","VisitNumber":1,"StopPointName":"ST JOHNS PL/KINGSTON AV"},{"Extensions":{"Distances":{"PresentableDistance":"1.7 miles away","DistanceFromCall":2692.01,"StopsFromCall":8,"CallDistanceAlongRoute":1810.41}},"StopPointRef":"MTA_303565","VisitNumber":1,"StopPointName":"ST JOHNS PL/BROOKLYN AV"},{"Extensions":{"Distances":{"PresentableDistance":"1.8 miles away","DistanceFromCall":2929.95,"StopsFromCall":9,"CallDistanceAlongRoute":2048.36}},"StopPointRef":"MTA_303566","VisitNumber":1,"StopPointName":"ST JOHNS PL/NEW YORK AV"},{"Extensions":{"Distances":{"PresentableDistance":"2.0 miles away","DistanceFromCall":3161.93,"StopsFromCall":10,"CallDistanceAlongRoute":2280.33}},"StopPointRef":"MTA_303567","VisitNumber":1,"StopPointName":"ST JOHNS PL/NOSTRAND AV"},{"Extensions":{"Distances":{"PresentableDistance":"2.1 miles away","DistanceFromCall":3395.92,"StopsFromCall":11,"CallDistanceAlongRoute":2514.32}},"StopPointRef":"MTA_303568","VisitNumber":1,"StopPointName":"ST JOHNS PL/ROGERS AV"},{"Extensions":{"Distances":{"PresentableDistance":"2.3 miles away","DistanceFromCall":3653.73,"StopsFromCall":12,"CallDistanceAlongRoute":2772.13}},"StopPointRef":"MTA_303569","VisitNumber":1,"StopPointName":"STERLING PL/BEDFORD AV"},{"Extensions":{"Distances":{"PresentableDistance":"2.4 miles away","DistanceFromCall":3886.57,"StopsFromCall":13,"CallDistanceAlongRoute":3004.97}},"StopPointRef":"MTA_303570","VisitNumber":1,"StopPointName":"STERLING PL/FRANKLIN AV"},{"Extensions":{"Distances":{"PresentableDistance":"2.6 miles away","DistanceFromCall":4136.21,"StopsFromCall":14,"CallDistanceAlongRoute":3254.61}},"StopPointRef":"MTA_308021","VisitNumber":1,"StopPointName":"STERLING PL/CLASSON AV"},{"Extensions":{"Distances":{"PresentableDistance":"2.7 miles away","DistanceFromCall":4375.14,"StopsFromCall":15,"CallDistanceAlongRoute":3493.54}},"StopPointRef":"MTA_303572","VisitNumber":1,"StopPointName":"STERLING PL/WASHINGTON AV"},{"Extensions":{"Distances":{"PresentableDistance":"2.9 miles away","DistanceFromCall":4647.63,"StopsFromCall":16,"CallDistanceAlongRoute":3766.03}},"StopPointRef":"MTA_303573","VisitNumber":1,"StopPointName":"WASHINGTON AV/PROSPECT PL"},{"Extensions":{"Distances":{"PresentableDistance":"3.0 miles away","DistanceFromCall":4865.83,"StopsFromCall":17,"CallDistanceAlongRoute":3984.23}},"StopPointRef":"MTA_303574","VisitNumber":1,"StopPointName":"WASHINGTON AV/BERGEN ST"},{"Extensions":{"Distances":{"PresentableDistance":"3.1 miles away","DistanceFromCall":5053.46,"StopsFromCall":18,"CallDistanceAlongRoute":4171.86}},"StopPointRef":"MTA_303575","VisitNumber":1,"StopPointName":"WASHINGTON AV/PACIFIC ST"},{"Extensions":{"Distances":{"PresentableDistance":"3.2 miles away","DistanceFromCall":5169.23,"StopsFromCall":19,"CallDistanceAlongRoute":4287.63}},"StopPointRef":"MTA_306514","VisitNumber":1,"StopPointName":"ATLANTIC AV/WASHINGTON AV"},{"Extensions":{"Distances":{"PresentableDistance":"3.3 miles away","DistanceFromCall":5268.43,"StopsFromCall":20,"CallDistanceAlongRoute":4386.84}},"StopPointRef":"MTA_303576","VisitNumber":1,"StopPointName":"ATLANTIC AV/WAVERLY AV"},{"Extensions":{"Distances":{"PresentableDistance":"3.4 miles away","DistanceFromCall":5452.96,"StopsFromCall":21,"CallDistanceAlongRoute":4571.36}},"StopPointRef":"MTA_303577","VisitNumber":1,"StopPointName":"ATLANTIC AV/VANDERBILT AV"},{"Extensions":{"Distances":{"PresentableDistance":"3.6 miles away","DistanceFromCall":5726.55,"StopsFromCall":22,"CallDistanceAlongRoute":4844.95}},"StopPointRef":"MTA_303578","VisitNumber":1,"StopPointName":"ATLANTIC AV/CARLTON AV"},{"Extensions":{"Distances":{"PresentableDistance":"3.6 miles away","DistanceFromCall":5815.98,"StopsFromCall":23,"CallDistanceAlongRoute":4934.38}},"StopPointRef":"MTA_801175","VisitNumber":1,"StopPointName":"ATLANTIC AV/CUMBERLAND ST"},{"Extensions":{"Distances":{"PresentableDistance":"4.0 miles away","DistanceFromCall":6367.55,"StopsFromCall":24,"CallDistanceAlongRoute":5485.95}},"StopPointRef":"MTA_303254","VisitNumber":1,"StopPointName":"FLATBUSH AV/ATLANTIC AV"},{"Extensions":{"Distances":{"PresentableDistance":"4.2 miles away","DistanceFromCall":6837.93,"StopsFromCall":25,"CallDistanceAlongRoute":5956.33}},"StopPointRef":"MTA_303256","VisitNumber":1,"StopPointName":"LIVINGSTON ST/NEVINS ST"},{"Extensions":{"Distances":{"PresentableDistance":"4.4 miles away","DistanceFromCall":7095.92,"StopsFromCall":26,"CallDistanceAlongRoute":6214.32}},"StopPointRef":"MTA_306892","VisitNumber":1,"StopPointName":"LIVINGSTON ST/BOND ST"},{"Extensions":{"Distances":{"PresentableDistance":"4.5 miles away","DistanceFromCall":7295.51,"StopsFromCall":27,"CallDistanceAlongRoute":6413.91}},"StopPointRef":"MTA_303258","VisitNumber":1,"StopPointName":"LIVINGSTON ST/HOYT ST"},{"Extensions":{"Distances":{"PresentableDistance":"4.6 miles away","DistanceFromCall":7448.54,"StopsFromCall":28,"CallDistanceAlongRoute":6566.94}},"StopPointRef":"MTA_303259","VisitNumber":1,"StopPointName":"LIVINGSTON ST/SMITH ST"},{"Extensions":{"Distances":{"PresentableDistance":"4.9 miles away","DistanceFromCall":7872.43,"StopsFromCall":29,"CallDistanceAlongRoute":6990.83}},"StopPointRef":"MTA_302434","VisitNumber":1,"StopPointName":"JORALEMON ST/COURT ST"},{"Extensions":{"Distances":{"PresentableDistance":"5.0 miles away","DistanceFromCall":8036.23,"StopsFromCall":30,"CallDistanceAlongRoute":7154.63}},"StopPointRef":"MTA_801026","VisitNumber":1,"StopPointName":"LIVINGSTON ST/COURT ST"}]}},"RecordedAtTime":"2014-11-19T17:23:17.000-05:00"},{"MonitoredVehicleJourney":{"LineRef":"MTA NYCT_B45","DirectionRef":"1","FramedVehicleJourneyRef":{"DataFrameRef":"2014-11-19","DatedVehicleJourneyRef":"MTA NYCT_EN_D4-Weekday-SDon-105300_B45_8"},"JourneyPatternRef":"MTA_B450028","PublishedLineName":"B45","OperatorRef":"MTA NYCT","OriginRef":"MTA_303557","DestinationRef":"MTA_801026","DestinationName":"DNTWN BKLYN COURT ST","OriginAimedDepartureTime":"2014-11-19T17:33:00.000-05:00","SituationRef":[{"SituationSimpleRef":"MTA NYCT_76244"}],"Monitored":true,"VehicleLocation":{"Longitude":-73.926906,"Latitude":40.67036},"Bearing":356.89993,"ProgressRate":"normalProgress","ProgressStatus":"prevTrip","BlockRef":"MTA NYCT_EN_D4-Weekday-SDon_E_EN_41760_B45-3","VehicleRef":"MTA NYCT_4833","MonitoredCall":{"Extensions":{"Distances":{"PresentableDistance":"3.2 miles away","DistanceFromCall":5207.04,"StopsFromCall":23,"CallDistanceAlongRoute":3984.23}},"StopPointRef":"MTA_303574","VisitNumber":1,"StopPointName":"WASHINGTON AV/BERGEN ST"},"OnwardCalls":{"OnwardCall":[{"Extensions":{"Distances":{"PresentableDistance":"0.8 miles away","DistanceFromCall":1223.01,"StopsFromCall":0,"CallDistanceAlongRoute":0.2}},"StopPointRef":"MTA_303557","VisitNumber":1,"StopPointName":"ST JOHNS PL/RALPH AV"},{"Extensions":{"Distances":{"PresentableDistance":"0.9 miles away","DistanceFromCall":1456.59,"StopsFromCall":1,"CallDistanceAlongRoute":233.78}},"StopPointRef":"MTA_303558","VisitNumber":1,"StopPointName":"ST JOHNS PL/BUFFALO AV"},{"Extensions":{"Distances":{"PresentableDistance":"1.0 miles away","DistanceFromCall":1676.53,"StopsFromCall":2,"CallDistanceAlongRoute":453.72}},"StopPointRef":"MTA_306894","VisitNumber":1,"StopPointName":"ST JOHNS PL/ROCHESTER AV"},{"Extensions":{"Distances":{"PresentableDistance":"1.2 miles away","DistanceFromCall":1864.32,"StopsFromCall":3,"CallDistanceAlongRoute":641.51}},"StopPointRef":"MTA_303560","VisitNumber":1,"StopPointName":"ST JOHNS PL/UTICA AV"},{"Extensions":{"Distances":{"PresentableDistance":"1.3 miles away","DistanceFromCall":2143.66,"StopsFromCall":4,"CallDistanceAlongRoute":920.85}},"StopPointRef":"MTA_303561","VisitNumber":1,"StopPointName":"ST JOHNS PL/SCHENECTADY AV"},{"Extensions":{"Distances":{"PresentableDistance":"1.5 miles away","DistanceFromCall":2377.88,"StopsFromCall":5,"CallDistanceAlongRoute":1155.07}},"StopPointRef":"MTA_303562","VisitNumber":1,"StopPointName":"ST JOHNS PL/TROY AV"},{"Extensions":{"Distances":{"PresentableDistance":"1.6 miles away","DistanceFromCall":2612.0,"StopsFromCall":6,"CallDistanceAlongRoute":1389.19}},"StopPointRef":"MTA_303563","VisitNumber":1,"StopPointName":"ST JOHNS PL/ALBANY AV"},{"Extensions":{"Distances":{"PresentableDistance":"1.7 miles away","DistanceFromCall":2799.86,"StopsFromCall":7,"CallDistanceAlongRoute":1577.05}},"StopPointRef":"MTA_303564","VisitNumber":1,"StopPointName":"ST JOHNS PL/KINGSTON AV"},{"Extensions":{"Distances":{"PresentableDistance":"1.9 miles away","DistanceFromCall":3033.23,"StopsFromCall":8,"CallDistanceAlongRoute":1810.41}},"StopPointRef":"MTA_303565","VisitNumber":1,"StopPointName":"ST JOHNS PL/BROOKLYN AV"},{"Extensions":{"Distances":{"PresentableDistance":"2.0 miles away","DistanceFromCall":3271.17,"StopsFromCall":9,"CallDistanceAlongRoute":2048.36}},"StopPointRef":"MTA_303566","VisitNumber":1,"StopPointName":"ST JOHNS PL/NEW YORK AV"},{"Extensions":{"Distances":{"PresentableDistance":"2.2 miles away","DistanceFromCall":3503.15,"StopsFromCall":10,"CallDistanceAlongRoute":2280.33}},"StopPointRef":"MTA_303567","VisitNumber":1,"StopPointName":"ST JOHNS PL/NOSTRAND AV"},{"Extensions":{"Distances":{"PresentableDistance":"2.3 miles away","DistanceFromCall":3737.14,"StopsFromCall":11,"CallDistanceAlongRoute":2514.32}},"StopPointRef":"MTA_303568","VisitNumber":1,"StopPointName":"ST JOHNS PL/ROGERS AV"},{"Extensions":{"Distances":{"PresentableDistance":"2.5 miles away","DistanceFromCall":3994.94,"StopsFromCall":12,"CallDistanceAlongRoute":2772.13}},"StopPointRef":"MTA_303569","VisitNumber":1,"StopPointName":"STERLING PL/BEDFORD AV"},{"Extensions":{"Distances":{"PresentableDistance":"2.6 miles away","DistanceFromCall":4227.78,"StopsFromCall":13,"CallDistanceAlongRoute":3004.97}},"StopPointRef":"MTA_303570","VisitNumber":1,"StopPointName":"STERLING PL/FRANKLIN AV"},{"Extensions":{"Distances":{"PresentableDistance":"2.8 miles away","DistanceFromCall":4477.42,"StopsFromCall":14,"CallDistanceAlongRoute":3254.61}},"StopPointRef":"MTA_308021","VisitNumber":1,"StopPointName":"STERLING PL/CLASSON AV"},{"Extensions":{"Distances":{"PresentableDistance":"2.9 miles away","DistanceFromCall":4716.36,"StopsFromCall":15,"CallDistanceAlongRoute":3493.54}},"StopPointRef":"MTA_303572","VisitNumber":1,"StopPointName":"STERLING PL/WASHINGTON AV"},{"Extensions":{"Distances":{"PresentableDistance":"3.1 miles away","DistanceFromCall":4988.85,"StopsFromCall":16,"CallDistanceAlongRoute":3766.03}},"StopPointRef":"MTA_303573","VisitNumber":1,"StopPointName":"WASHINGTON AV/PROSPECT PL"},{"Extensions":{"Distances":{"PresentableDistance":"3.2 miles away","DistanceFromCall":5207.04,"StopsFromCall":17,"CallDistanceAlongRoute":3984.23}},"StopPointRef":"MTA_303574","VisitNumber":1,"StopPointName":"WASHINGTON AV/BERGEN ST"},{"Extensions":{"Distances":{"PresentableDistance":"3.4 miles away","DistanceFromCall":5394.67,"StopsFromCall":18,"CallDistanceAlongRoute":4171.86}},"StopPointRef":"MTA_303575","VisitNumber":1,"StopPointName":"WASHINGTON AV/PACIFIC ST"},{"Extensions":{"Distances":{"PresentableDistance":"3.4 miles away","DistanceFromCall":5510.44,"StopsFromCall":19,"CallDistanceAlongRoute":4287.63}},"StopPointRef":"MTA_306514","VisitNumber":1,"StopPointName":"ATLANTIC AV/WASHINGTON AV"},{"Extensions":{"Distances":{"PresentableDistance":"3.5 miles away","DistanceFromCall":5609.65,"StopsFromCall":20,"CallDistanceAlongRoute":4386.84}},"StopPointRef":"MTA_303576","VisitNumber":1,"StopPointName":"ATLANTIC AV/WAVERLY AV"},{"Extensions":{"Distances":{"PresentableDistance":"3.6 miles away","DistanceFromCall":5794.17,"StopsFromCall":21,"CallDistanceAlongRoute":4571.36}},"StopPointRef":"MTA_303577","VisitNumber":1,"StopPointName":"ATLANTIC AV/VANDERBILT AV"},{"Extensions":{"Distances":{"PresentableDistance":"3.8 miles away","DistanceFromCall":6067.77,"StopsFromCall":22,"CallDistanceAlongRoute":4844.95}},"StopPointRef":"MTA_303578","VisitNumber":1,"StopPointName":"ATLANTIC AV/CARLTON AV"},{"Extensions":{"Distances":{"PresentableDistance":"3.8 miles away","DistanceFromCall":6157.19,"StopsFromCall":23,"CallDistanceAlongRoute":4934.38}},"StopPointRef":"MTA_801175","VisitNumber":1,"StopPointName":"ATLANTIC AV/CUMBERLAND ST"},{"Extensions":{"Distances":{"PresentableDistance":"4.2 miles away","DistanceFromCall":6708.77,"StopsFromCall":24,"CallDistanceAlongRoute":5485.95}},"StopPointRef":"MTA_303254","VisitNumber":1,"StopPointName":"FLATBUSH AV/ATLANTIC AV"},{"Extensions":{"Distances":{"PresentableDistance":"4.5 miles away","DistanceFromCall":7179.14,"StopsFromCall":25,"CallDistanceAlongRoute":5956.33}},"StopPointRef":"MTA_303256","VisitNumber":1,"StopPointName":"LIVINGSTON ST/NEVINS ST"},{"Extensions":{"Distances":{"PresentableDistance":"4.6 miles away","DistanceFromCall":7437.14,"StopsFromCall":26,"CallDistanceAlongRoute":6214.32}},"StopPointRef":"MTA_306892","VisitNumber":1,"StopPointName":"LIVINGSTON ST/BOND ST"},{"Extensions":{"Distances":{"PresentableDistance":"4.7 miles away","DistanceFromCall":7636.73,"StopsFromCall":27,"CallDistanceAlongRoute":6413.91}},"StopPointRef":"MTA_303258","VisitNumber":1,"StopPointName":"LIVINGSTON ST/HOYT ST"},{"Extensions":{"Distances":{"PresentableDistance":"4.8 miles away","DistanceFromCall":7789.75,"StopsFromCall":28,"CallDistanceAlongRoute":6566.94}},"StopPointRef":"MTA_303259","VisitNumber":1,"StopPointName":"LIVINGSTON ST/SMITH ST"},{"Extensions":{"Distances":{"PresentableDistance":"5.1 miles away","DistanceFromCall":8213.65,"StopsFromCall":29,"CallDistanceAlongRoute":6990.83}},"StopPointRef":"MTA_302434","VisitNumber":1,"StopPointName":"JORALEMON ST/COURT ST"},{"Extensions":{"Distances":{"PresentableDistance":"5.2 miles away","DistanceFromCall":8377.44,"StopsFromCall":30,"CallDistanceAlongRoute":7154.63}},"StopPointRef":"MTA_801026","VisitNumber":1,"StopPointName":"LIVINGSTON ST/COURT ST"}]}},"RecordedAtTime":"2014-11-19T17:23:24.000-05:00"},{"MonitoredVehicleJourney":{"LineRef":"MTA NYCT_B45","DirectionRef":"1","FramedVehicleJourneyRef":{"DataFrameRef":"2014-11-19","DatedVehicleJourneyRef":"MTA NYCT_EN_D4-Weekday-SDon-104200_B45_16"},"JourneyPatternRef":"MTA_B450028","PublishedLineName":"B45","OperatorRef":"MTA NYCT","OriginRef":"MTA_303557","DestinationRef":"MTA_801026","DestinationName":"DNTWN BKLYN COURT ST","OriginAimedDepartureTime":"2014-11-19T16:19:00.000-05:00","SituationRef":[{"SituationSimpleRef":"MTA NYCT_76244"}],"Monitored":true,"VehicleLocation":{"Longitude":-73.964513,"Latitude":40.681055},"Bearing":348.23172,"ProgressRate":"normalProgress","ProgressStatus":"prevTrip","BlockRef":"MTA NYCT_EN_D4-Weekday-SDon_E_EN_47520_B65-113","VehicleRef":"MTA NYCT_6834","MonitoredCall":{"Extensions":{"Distances":{"PresentableDistance":"5.7 miles away","DistanceFromCall":9126.06,"StopsFromCall":42,"CallDistanceAlongRoute":3984.23}},"StopPointRef":"MTA_303574","VisitNumber":1,"StopPointName":"WASHINGTON AV/BERGEN ST"},"OnwardCalls":{"OnwardCall":[{"Extensions":{"Distances":{"PresentableDistance":"3.2 miles away","DistanceFromCall":5142.02,"StopsFromCall":0,"CallDistanceAlongRoute":0.2}},"StopPointRef":"MTA_303557","VisitNumber":1,"StopPointName":"ST JOHNS PL/RALPH AV"},{"Extensions":{"Distances":{"PresentableDistance":"3.3 miles away","DistanceFromCall":5375.61,"StopsFromCall":1,"CallDistanceAlongRoute":233.78}},"StopPointRef":"MTA_303558","VisitNumber":1,"StopPointName":"ST JOHNS PL/BUFFALO AV"},{"Extensions":{"Distances":{"PresentableDistance":"3.5 miles away","DistanceFromCall":5595.54,"StopsFromCall":2,"CallDistanceAlongRoute":453.72}},"StopPointRef":"MTA_306894","VisitNumber":1,"StopPointName":"ST JOHNS PL/ROCHESTER AV"},{"Extensions":{"Distances":{"PresentableDistance":"3.6 miles away","DistanceFromCall":5783.34,"StopsFromCall":3,"CallDistanceAlongRoute":641.51}},"StopPointRef":"MTA_303560","VisitNumber":1,"StopPointName":"ST JOHNS PL/UTICA AV"},{"Extensions":{"Distances":{"PresentableDistance":"3.8 miles away","DistanceFromCall":6062.67,"StopsFromCall":4,"CallDistanceAlongRoute":920.85}},"StopPointRef":"MTA_303561","VisitNumber":1,"StopPointName":"ST JOHNS PL/SCHENECTADY AV"},{"Extensions":{"Distances":{"PresentableDistance":"3.9 miles away","DistanceFromCall":6296.89,"StopsFromCall":5,"CallDistanceAlongRoute":1155.07}},"StopPointRef":"MTA_303562","VisitNumber":1,"StopPointName":"ST JOHNS PL/TROY AV"},{"Extensions":{"Distances":{"PresentableDistance":"4.1 miles away","DistanceFromCall":6531.01,"StopsFromCall":6,"CallDistanceAlongRoute":1389.19}},"StopPointRef":"MTA_303563","VisitNumber":1,"StopPointName":"ST JOHNS PL/ALBANY AV"},{"Extensions":{"Distances":{"PresentableDistance":"4.2 miles away","DistanceFromCall":6718.87,"StopsFromCall":7,"CallDistanceAlongRoute":1577.05}},"StopPointRef":"MTA_303564","VisitNumber":1,"StopPointName":"ST JOHNS PL/KINGSTON AV"},{"Extensions":{"Distances":{"PresentableDistance":"4.3 miles away","DistanceFromCall":6952.24,"StopsFromCall":8,"CallDistanceAlongRoute":1810.41}},"StopPointRef":"MTA_303565","VisitNumber":1,"StopPointName":"ST JOHNS PL/BROOKLYN AV"},{"Extensions":{"Distances":{"PresentableDistance":"4.5 miles away","DistanceFromCall":7190.18,"StopsFromCall":9,"CallDistanceAlongRoute":2048.36}},"StopPointRef":"MTA_303566","VisitNumber":1,"StopPointName":"ST JOHNS PL/NEW YORK AV"},{"Extensions":{"Distances":{"PresentableDistance":"4.6 miles away","DistanceFromCall":7422.16,"StopsFromCall":10,"CallDistanceAlongRoute":2280.33}},"StopPointRef":"MTA_303567","VisitNumber":1,"StopPointName":"ST JOHNS PL/NOSTRAND AV"},{"Extensions":{"Distances":{"PresentableDistance":"4.8 miles away","DistanceFromCall":7656.15,"StopsFromCall":11,"CallDistanceAlongRoute":2514.32}},"StopPointRef":"MTA_303568","VisitNumber":1,"StopPointName":"ST JOHNS PL/ROGERS AV"},{"Extensions":{"Distances":{"PresentableDistance":"4.9 miles away","DistanceFromCall":7913.95,"StopsFromCall":12,"CallDistanceAlongRoute":2772.13}},"StopPointRef":"MTA_303569","VisitNumber":1,"StopPointName":"STERLING PL/BEDFORD AV"},{"Extensions":{"Distances":{"PresentableDistance":"5.1 miles away","DistanceFromCall":8146.79,"StopsFromCall":13,"CallDistanceAlongRoute":3004.97}},"StopPointRef":"MTA_303570","VisitNumber":1,"StopPointName":"STERLING PL/FRANKLIN AV"},{"Extensions":{"Distances":{"PresentableDistance":"5.2 miles away","DistanceFromCall":8396.43,"StopsFromCall":14,"CallDistanceAlongRoute":3254.61}},"StopPointRef":"MTA_308021","VisitNumber":1,"StopPointName":"STERLING PL/CLASSON AV"},{"Extensions":{"Distances":{"PresentableDistance":"5.4 miles away","DistanceFromCall":8635.37,"StopsFromCall":15,"CallDistanceAlongRoute":3493.54}},"StopPointRef":"MTA_303572","VisitNumber":1,"StopPointName":"STERLING PL/WASHINGTON AV"},{"Extensions":{"Distances":{"PresentableDistance":"5.5 miles away","DistanceFromCall":8907.86,"StopsFromCall":16,"CallDistanceAlongRoute":3766.03}},"StopPointRef":"MTA_303573","VisitNumber":1,"StopPointName":"WASHINGTON AV/PROSPECT PL"},{"Extensions":{"Distances":{"PresentableDistance":"5.7 miles away","DistanceFromCall":9126.06,"StopsFromCall":17,"CallDistanceAlongRoute":3984.23}},"StopPointRef":"MTA_303574","VisitNumber":1,"StopPointName":"WASHINGTON AV/BERGEN ST"},{"Extensions":{"Distances":{"PresentableDistance":"5.8 miles away","DistanceFromCall":9313.69,"StopsFromCall":18,"CallDistanceAlongRoute":4171.86}},"StopPointRef":"MTA_303575","VisitNumber":1,"StopPointName":"WASHINGTON AV/PACIFIC ST"},{"Extensions":{"Distances":{"PresentableDistance":"5.9 miles away","DistanceFromCall":9429.45,"StopsFromCall":19,"CallDistanceAlongRoute":4287.63}},"StopPointRef":"MTA_306514","VisitNumber":1,"StopPointName":"ATLANTIC AV/WASHINGTON AV"},{"Extensions":{"Distances":{"PresentableDistance":"5.9 miles away","DistanceFromCall":9528.66,"StopsFromCall":20,"CallDistanceAlongRoute":4386.84}},"StopPointRef":"MTA_303576","VisitNumber":1,"StopPointName":"ATLANTIC AV/WAVERLY AV"},{"Extensions":{"Distances":{"PresentableDistance":"6.0 miles away","DistanceFromCall":9713.18,"StopsFromCall":21,"CallDistanceAlongRoute":4571.36}},"StopPointRef":"MTA_303577","VisitNumber":1,"StopPointName":"ATLANTIC AV/VANDERBILT AV"},{"Extensions":{"Distances":{"PresentableDistance":"6.2 miles away","DistanceFromCall":9986.78,"StopsFromCall":22,"CallDistanceAlongRoute":4844.95}},"StopPointRef":"MTA_303578","VisitNumber":1,"StopPointName":"ATLANTIC AV/CARLTON AV"},{"Extensions":{"Distances":{"PresentableDistance":"6.3 miles away","DistanceFromCall":10076.21,"StopsFromCall":23,"CallDistanceAlongRoute":4934.38}},"StopPointRef":"MTA_801175","VisitNumber":1,"StopPointName":"ATLANTIC AV/CUMBERLAND ST"},{"Extensions":{"Distances":{"PresentableDistance":"6.6 miles away","DistanceFromCall":10627.78,"StopsFromCall":24,"CallDistanceAlongRoute":5485.95}},"StopPointRef":"MTA_303254","VisitNumber":1,"StopPointName":"FLATBUSH AV/ATLANTIC AV"},{"Extensions":{"Distances":{"PresentableDistance":"6.9 miles away","DistanceFromCall":11098.16,"StopsFromCall":25,"CallDistanceAlongRoute":5956.33}},"StopPointRef":"MTA_303256","VisitNumber":1,"StopPointName":"LIVINGSTON ST/NEVINS ST"},{"Extensions":{"Distances":{"PresentableDistance":"7.1 miles away","DistanceFromCall":11356.15,"StopsFromCall":26,"CallDistanceAlongRoute":6214.32}},"StopPointRef":"MTA_306892","VisitNumber":1,"StopPointName":"LIVINGSTON ST/BOND ST"},{"Extensions":{"Distances":{"PresentableDistance":"7.2 miles away","DistanceFromCall":11555.74,"StopsFromCall":27,"CallDistanceAlongRoute":6413.91}},"StopPointRef":"MTA_303258","VisitNumber":1,"StopPointName":"LIVINGSTON ST/HOYT ST"},{"Extensions":{"Distances":{"PresentableDistance":"7.3 miles away","DistanceFromCall":11708.76,"StopsFromCall":28,"CallDistanceAlongRoute":6566.94}},"StopPointRef":"MTA_303259","VisitNumber":1,"StopPointName":"LIVINGSTON ST/SMITH ST"},{"Extensions":{"Distances":{"PresentableDistance":"7.5 miles away","DistanceFromCall":12132.66,"StopsFromCall":29,"CallDistanceAlongRoute":6990.83}},"StopPointRef":"MTA_302434","VisitNumber":1,"StopPointName":"JORALEMON ST/COURT ST"},{"Extensions":{"Distances":{"PresentableDistance":"7.6 miles away","DistanceFromCall":12296.46,"StopsFromCall":30,"CallDistanceAlongRoute":7154.63}},"StopPointRef":"MTA_801026","VisitNumber":1,"StopPointName":"LIVINGSTON ST/COURT ST"}]}},"RecordedAtTime":"2014-11-19T17:22:55.000-05:00"},{"MonitoredVehicleJourney":{"LineRef":"MTA NYCT_B45","DirectionRef":"1","FramedVehicleJourneyRef":{"DataFrameRef":"2014-11-19","DatedVehicleJourneyRef":"MTA NYCT_EN_D4-Weekday-SDon-106500_B65_116"},"JourneyPatternRef":"MTA_B450028","PublishedLineName":"B45","OperatorRef":"MTA NYCT","OriginRef":"MTA_303557","DestinationRef":"MTA_801026","DestinationName":"DNTWN BKLYN COURT ST","OriginAimedDepartureTime":"2014-11-19T16:48:00.000-05:00","SituationRef":[{"SituationSimpleRef":"MTA NYCT_76244"}],"Monitored":true,"VehicleLocation":{"Longitude":-73.965604,"Latitude":40.681284},"Bearing":348.1416,"ProgressRate":"normalProgress","ProgressStatus":"prevTrip","BlockRef":"MTA NYCT_EN_D4-Weekday-SDon_E_EN_29520_B45-9","VehicleRef":"MTA NYCT_4811","MonitoredCall":{"Extensions":{"Distances":{"PresentableDistance":"5.7 miles away","DistanceFromCall":9221.52,"StopsFromCall":42,"CallDistanceAlongRoute":3984.23}},"StopPointRef":"MTA_303574","VisitNumber":1,"StopPointName":"WASHINGTON AV/BERGEN ST"},"OnwardCalls":{"OnwardCall":[{"Extensions":{"Distances":{"PresentableDistance":"3.3 miles away","DistanceFromCall":5237.48,"StopsFromCall":0,"CallDistanceAlongRoute":0.2}},"StopPointRef":"MTA_303557","VisitNumber":1,"StopPointName":"ST JOHNS PL/RALPH AV"},{"Extensions":{"Distances":{"PresentableDistance":"3.4 miles away","DistanceFromCall":5471.07,"StopsFromCall":1,"CallDistanceAlongRoute":233.78}},"StopPointRef":"MTA_303558","VisitNumber":1,"StopPointName":"ST JOHNS PL/BUFFALO AV"},{"Extensions":{"Distances":{"PresentableDistance":"3.5 miles away","DistanceFromCall":5691.0,"StopsFromCall":2,"CallDistanceAlongRoute":453.72}},"StopPointRef":"MTA_306894","VisitNumber":1,"StopPointName":"ST JOHNS PL/ROCHESTER AV"},{"Extensions":{"Distances":{"PresentableDistance":"3.7 miles away","DistanceFromCall":5878.8,"StopsFromCall":3,"CallDistanceAlongRoute":641.51}},"StopPointRef":"MTA_303560","VisitNumber":1,"StopPointName":"ST JOHNS PL/UTICA AV"},{"Extensions":{"Distances":{"PresentableDistance":"3.8 miles away","DistanceFromCall":6158.14,"StopsFromCall":4,"CallDistanceAlongRoute":920.85}},"StopPointRef":"MTA_303561","VisitNumber":1,"StopPointName":"ST JOHNS PL/SCHENECTADY AV"},{"Extensions":{"Distances":{"PresentableDistance":"4.0 miles away","DistanceFromCall":6392.36,"StopsFromCall":5,"CallDistanceAlongRoute":1155.07}},"StopPointRef":"MTA_303562","VisitNumber":1,"StopPointName":"ST JOHNS PL/TROY AV"},{"Extensions":{"Distances":{"PresentableDistance":"4.1 miles away","DistanceFromCall":6626.48,"StopsFromCall":6,"CallDistanceAlongRoute":1389.19}},"StopPointRef":"MTA_303563","VisitNumber":1,"StopPointName":"ST JOHNS PL/ALBANY AV"},{"Extensions":{"Distances":{"PresentableDistance":"4.2 miles away","DistanceFromCall":6814.34,"StopsFromCall":7,"CallDistanceAlongRoute":1577.05}},"StopPointRef":"MTA_303564","VisitNumber":1,"StopPointName":"ST JOHNS PL/KINGSTON AV"},{"Extensions":{"Distances":{"PresentableDistance":"4.4 miles away","DistanceFromCall":7047.7,"StopsFromCall":8,"CallDistanceAlongRoute":1810.41}},"StopPointRef":"MTA_303565","VisitNumber":1,"StopPointName":"ST JOHNS PL/BROOKLYN AV"},{"Extensions":{"Distances":{"PresentableDistance":"4.5 miles away","DistanceFromCall":7285.64,"StopsFromCall":9,"CallDistanceAlongRoute":2048.36}},"StopPointRef":"MTA_303566","VisitNumber":1,"StopPointName":"ST JOHNS PL/NEW YORK AV"},{"Extensions":{"Distances":{"PresentableDistance":"4.7 miles away","DistanceFromCall":7517.62,"StopsFromCall":10,"CallDistanceAlongRoute":2280.33}},"StopPointRef":"MTA_303567","VisitNumber":1,"StopPointName":"ST JOHNS PL/NOSTRAND AV"},{"Extensions":{"Distances":{"PresentableDistance":"4.8 miles away","DistanceFromCall":7751.61,"StopsFromCall":11,"CallDistanceAlongRoute":2514.32}},"StopPointRef":"MTA_303568","VisitNumber":1,"StopPointName":"ST JOHNS PL/ROGERS AV"},{"Extensions":{"Distances":{"PresentableDistance":"5.0 miles away","DistanceFromCall":8009.42,"StopsFromCall":12,"CallDistanceAlongRoute":2772.13}},"StopPointRef":"MTA_303569","VisitNumber":1,"StopPointName":"STERLING PL/BEDFORD AV"},{"Extensions":{"Distances":{"PresentableDistance":"5.1 miles away","DistanceFromCall":8242.26,"StopsFromCall":13,"CallDistanceAlongRoute":3004.97}},"StopPointRef":"MTA_303570","VisitNumber":1,"StopPointName":"STERLING PL/FRANKLIN AV"},{"Extensions":{"Distances":{"PresentableDistance":"5.3 miles away","DistanceFromCall":8491.9,"StopsFromCall":14,"CallDistanceAlongRoute":3254.61}},"StopPointRef":"MTA_308021","VisitNumber":1,"StopPointName":"STERLING PL/CLASSON AV"},{"Extensions":{"Distances":{"PresentableDistance":"5.4 miles away","DistanceFromCall":8730.83,"StopsFromCall":15,"CallDistanceAlongRoute":3493.54}},"StopPointRef":"MTA_303572","VisitNumber":1,"StopPointName":"STERLING PL/WASHINGTON AV"},{"Extensions":{"Distances":{"PresentableDistance":"5.6 miles away","DistanceFromCall":9003.32,"StopsFromCall":16,"CallDistanceAlongRoute":3766.03}},"StopPointRef":"MTA_303573","VisitNumber":1,"StopPointName":"WASHINGTON AV/PROSPECT PL"},{"Extensions":{"Distances":{"PresentableDistance":"5.7 miles away","DistanceFromCall":9221.52,"StopsFromCall":17,"CallDistanceAlongRoute":3984.23}},"StopPointRef":"MTA_303574","VisitNumber":1,"StopPointName":"WASHINGTON AV/BERGEN ST"},{"Extensions":{"Distances":{"PresentableDistance":"5.8 miles away","DistanceFromCall":9409.15,"StopsFromCall":18,"CallDistanceAlongRoute":4171.86}},"StopPointRef":"MTA_303575","VisitNumber":1,"StopPointName":"WASHINGTON AV/PACIFIC ST"},{"Extensions":{"Distances":{"PresentableDistance":"5.9 miles away","DistanceFromCall":9524.92,"StopsFromCall":19,"CallDistanceAlongRoute":4287.63}},"StopPointRef":"MTA_306514","VisitNumber":1,"StopPointName":"ATLANTIC AV/WASHINGTON AV"},{"Extensions":{"Distances":{"PresentableDistance":"6.0 miles away","DistanceFromCall":9624.12,"StopsFromCall":20,"CallDistanceAlongRoute":4386.84}},"StopPointRef":"MTA_303576","VisitNumber":1,"StopPointName":"ATLANTIC AV/WAVERLY AV"},{"Extensions":{"Distances":{"PresentableDistance":"6.1 miles away","DistanceFromCall":9808.65,"StopsFromCall":21,"CallDistanceAlongRoute":4571.36}},"StopPointRef":"MTA_303577","VisitNumber":1,"StopPointName":"ATLANTIC AV/VANDERBILT AV"},{"Extensions":{"Distances":{"PresentableDistance":"6.3 miles away","DistanceFromCall":10082.24,"StopsFromCall":22,"CallDistanceAlongRoute":4844.95}},"StopPointRef":"MTA_303578","VisitNumber":1,"StopPointName":"ATLANTIC AV/CARLTON AV"},{"Extensions":{"Distances":{"PresentableDistance":"6.3 miles away","DistanceFromCall":10171.67,"StopsFromCall":23,"CallDistanceAlongRoute":4934.38}},"StopPointRef":"MTA_801175","VisitNumber":1,"StopPointName":"ATLANTIC AV/CUMBERLAND ST"},{"Extensions":{"Distances":{"PresentableDistance":"6.7 miles away","DistanceFromCall":10723.24,"StopsFromCall":24,"CallDistanceAlongRoute":5485.95}},"StopPointRef":"MTA_303254","VisitNumber":1,"StopPointName":"FLATBUSH AV/ATLANTIC AV"},{"Extensions":{"Distances":{"PresentableDistance":"7.0 miles away","DistanceFromCall":11193.62,"StopsFromCall":25,"CallDistanceAlongRoute":5956.33}},"StopPointRef":"MTA_303256","VisitNumber":1,"StopPointName":"LIVINGSTON ST/NEVINS ST"},{"Extensions":{"Distances":{"PresentableDistance":"7.1 miles away","DistanceFromCall":11451.61,"StopsFromCall":26,"CallDistanceAlongRoute":6214.32}},"StopPointRef":"MTA_306892","VisitNumber":1,"StopPointName":"LIVINGSTON ST/BOND ST"},{"Extensions":{"Distances":{"PresentableDistance":"7.2 miles away","DistanceFromCall":11651.2,"StopsFromCall":27,"CallDistanceAlongRoute":6413.91}},"StopPointRef":"MTA_303258","VisitNumber":1,"StopPointName":"LIVINGSTON ST/HOYT ST"},{"Extensions":{"Distances":{"PresentableDistance":"7.3 miles away","DistanceFromCall":11804.23,"StopsFromCall":28,"CallDistanceAlongRoute":6566.94}},"StopPointRef":"MTA_303259","VisitNumber":1,"StopPointName":"LIVINGSTON ST/SMITH ST"},{"Extensions":{"Distances":{"PresentableDistance":"7.6 miles away","DistanceFromCall":12228.12,"StopsFromCall":29,"CallDistanceAlongRoute":6990.83}},"StopPointRef":"MTA_302434","VisitNumber":1,"StopPointName":"JORALEMON ST/COURT ST"},{"Extensions":{"Distances":{"PresentableDistance":"7.7 miles away","DistanceFromCall":12391.92,"StopsFromCall":30,"CallDistanceAlongRoute":7154.63}},"StopPointRef":"MTA_801026","VisitNumber":1,"StopPointName":"LIVINGSTON ST/COURT ST"}]}},"RecordedAtTime":"2014-11-19T17:23:23.000-05:00"},{"MonitoredVehicleJourney":{"LineRef":"MTA NYCT_B45","DirectionRef":"1","FramedVehicleJourneyRef":{"DataFrameRef":"2014-11-19","DatedVehicleJourneyRef":"MTA NYCT_EN_D4-Weekday-SDon-108900_B45_18"},"JourneyPatternRef":"MTA_B450028","PublishedLineName":"B45","OperatorRef":"MTA NYCT","OriginRef":"MTA_303557","DestinationRef":"MTA_801026","DestinationName":"DNTWN BKLYN COURT ST","OriginAimedDepartureTime":"2014-11-19T17:08:00.000-05:00","SituationRef":[{"SituationSimpleRef":"MTA NYCT_76244"}],"Monitored":true,"VehicleLocation":{"Longitude":-73.985614,"Latitude":40.689582},"Bearing":338.905,"ProgressRate":"normalProgress","ProgressStatus":"prevTrip","BlockRef":"MTA NYCT_EN_D4-Weekday-SDon_E_EN_43920_B45-11","VehicleRef":"MTA NYCT_6591","MonitoredCall":{"Extensions":{"Distances":{"PresentableDistance":"7.0 miles away","DistanceFromCall":11276.29,"StopsFromCall":49,"CallDistanceAlongRoute":3984.23}},"StopPointRef":"MTA_303574","VisitNumber":1,"StopPointName":"WASHINGTON AV/BERGEN ST"},"OnwardCalls":{"OnwardCall":[{"Extensions":{"Distances":{"PresentableDistance":"4.5 miles away","DistanceFromCall":7292.26,"StopsFromCall":0,"CallDistanceAlongRoute":0.2}},"StopPointRef":"MTA_303557","VisitNumber":1,"StopPointName":"ST JOHNS PL/RALPH AV"},{"Extensions":{"Distances":{"PresentableDistance":"4.7 miles away","DistanceFromCall":7525.84,"StopsFromCall":1,"CallDistanceAlongRoute":233.78}},"StopPointRef":"MTA_303558","VisitNumber":1,"StopPointName":"ST JOHNS PL/BUFFALO AV"},{"Extensions":{"Distances":{"PresentableDistance":"4.8 miles away","DistanceFromCall":7745.78,"StopsFromCall":2,"CallDistanceAlongRoute":453.72}},"StopPointRef":"MTA_306894","VisitNumber":1,"StopPointName":"ST JOHNS PL/ROCHESTER AV"},{"Extensions":{"Distances":{"PresentableDistance":"4.9 miles away","DistanceFromCall":7933.57,"StopsFromCall":3,"CallDistanceAlongRoute":641.51}},"StopPointRef":"MTA_303560","VisitNumber":1,"StopPointName":"ST JOHNS PL/UTICA AV"},{"Extensions":{"Distances":{"PresentableDistance":"5.1 miles away","DistanceFromCall":8212.91,"StopsFromCall":4,"CallDistanceAlongRoute":920.85}},"StopPointRef":"MTA_303561","VisitNumber":1,"StopPointName":"ST JOHNS PL/SCHENECTADY AV"},{"Extensions":{"Distances":{"PresentableDistance":"5.2 miles away","DistanceFromCall":8447.13,"StopsFromCall":5,"CallDistanceAlongRoute":1155.07}},"StopPointRef":"MTA_303562","VisitNumber":1,"StopPointName":"ST JOHNS PL/TROY AV"},{"Extensions":{"Distances":{"PresentableDistance":"5.4 miles away","DistanceFromCall":8681.25,"StopsFromCall":6,"CallDistanceAlongRoute":1389.19}},"StopPointRef":"MTA_303563","VisitNumber":1,"StopPointName":"ST JOHNS PL/ALBANY AV"},{"Extensions":{"Distances":{"PresentableDistance":"5.5 miles away","DistanceFromCall":8869.11,"StopsFromCall":7,"CallDistanceAlongRoute":1577.05}},"StopPointRef":"MTA_303564","VisitNumber":1,"StopPointName":"ST JOHNS PL/KINGSTON AV"},{"Extensions":{"Distances":{"PresentableDistance":"5.7 miles away","DistanceFromCall":9102.48,"StopsFromCall":8,"CallDistanceAlongRoute":1810.41}},"StopPointRef":"MTA_303565","VisitNumber":1,"StopPointName":"ST JOHNS PL/BROOKLYN AV"},{"Extensions":{"Distances":{"PresentableDistance":"5.8 miles away","DistanceFromCall":9340.42,"StopsFromCall":9,"CallDistanceAlongRoute":2048.36}},"StopPointRef":"MTA_303566","VisitNumber":1,"StopPointName":"ST JOHNS PL/NEW YORK AV"},{"Extensions":{"Distances":{"PresentableDistance":"5.9 miles away","DistanceFromCall":9572.39,"StopsFromCall":10,"CallDistanceAlongRoute":2280.33}},"StopPointRef":"MTA_303567","VisitNumber":1,"StopPointName":"ST JOHNS PL/NOSTRAND AV"},{"Extensions":{"Distances":{"PresentableDistance":"6.1 miles away","DistanceFromCall":9806.38,"StopsFromCall":11,"CallDistanceAlongRoute":2514.32}},"StopPointRef":"MTA_303568","VisitNumber":1,"StopPointName":"ST JOHNS PL/ROGERS AV"},{"Extensions":{"Distances":{"PresentableDistance":"6.3 miles away","DistanceFromCall":10064.19,"StopsFromCall":12,"CallDistanceAlongRoute":2772.13}},"StopPointRef":"MTA_303569","VisitNumber":1,"StopPointName":"STERLING PL/BEDFORD AV"},{"Extensions":{"Distances":{"PresentableDistance":"6.4 miles away","DistanceFromCall":10297.03,"StopsFromCall":13,"CallDistanceAlongRoute":3004.97}},"StopPointRef":"MTA_303570","VisitNumber":1,"StopPointName":"STERLING PL/FRANKLIN AV"},{"Extensions":{"Distances":{"PresentableDistance":"6.6 miles away","DistanceFromCall":10546.67,"StopsFromCall":14,"CallDistanceAlongRoute":3254.61}},"StopPointRef":"MTA_308021","VisitNumber":1,"StopPointName":"STERLING PL/CLASSON AV"},{"Extensions":{"Distances":{"PresentableDistance":"6.7 miles away","DistanceFromCall":10785.61,"StopsFromCall":15,"CallDistanceAlongRoute":3493.54}},"StopPointRef":"MTA_303572","VisitNumber":1,"StopPointName":"STERLING PL/WASHINGTON AV"},{"Extensions":{"Distances":{"PresentableDistance":"6.9 miles away","DistanceFromCall":11058.09,"StopsFromCall":16,"CallDistanceAlongRoute":3766.03}},"StopPointRef":"MTA_303573","VisitNumber":1,"StopPointName":"WASHINGTON AV/PROSPECT PL"},{"Extensions":{"Distances":{"PresentableDistance":"7.0 miles away","DistanceFromCall":11276.29,"StopsFromCall":17,"CallDistanceAlongRoute":3984.23}},"StopPointRef":"MTA_303574","VisitNumber":1,"StopPointName":"WASHINGTON AV/BERGEN ST"},{"Extensions":{"Distances":{"PresentableDistance":"7.1 miles away","DistanceFromCall":11463.92,"StopsFromCall":18,"CallDistanceAlongRoute":4171.86}},"StopPointRef":"MTA_303575","VisitNumber":1,"StopPointName":"WASHINGTON AV/PACIFIC ST"},{"Extensions":{"Distances":{"PresentableDistance":"7.2 miles away","DistanceFromCall":11579.69,"StopsFromCall":19,"CallDistanceAlongRoute":4287.63}},"StopPointRef":"MTA_306514","VisitNumber":1,"StopPointName":"ATLANTIC AV/WASHINGTON AV"},{"Extensions":{"Distances":{"PresentableDistance":"7.3 miles away","DistanceFromCall":11678.9,"StopsFromCall":20,"CallDistanceAlongRoute":4386.84}},"StopPointRef":"MTA_303576","VisitNumber":1,"StopPointName":"ATLANTIC AV/WAVERLY AV"},{"Extensions":{"Distances":{"PresentableDistance":"7.4 miles away","DistanceFromCall":11863.42,"StopsFromCall":21,"CallDistanceAlongRoute":4571.36}},"StopPointRef":"MTA_303577","VisitNumber":1,"StopPointName":"ATLANTIC AV/VANDERBILT AV"},{"Extensions":{"Distances":{"PresentableDistance":"7.5 miles away","DistanceFromCall":12137.01,"StopsFromCall":22,"CallDistanceAlongRoute":4844.95}},"StopPointRef":"MTA_303578","VisitNumber":1,"StopPointName":"ATLANTIC AV/CARLTON AV"},{"Extensions":{"Distances":{"PresentableDistance":"7.6 miles away","DistanceFromCall":12226.44,"StopsFromCall":23,"CallDistanceAlongRoute":4934.38}},"StopPointRef":"MTA_801175","VisitNumber":1,"StopPointName":"ATLANTIC AV/CUMBERLAND ST"},{"Extensions":{"Distances":{"PresentableDistance":"7.9 miles away","DistanceFromCall":12778.01,"StopsFromCall":24,"CallDistanceAlongRoute":5485.95}},"StopPointRef":"MTA_303254","VisitNumber":1,"StopPointName":"FLATBUSH AV/ATLANTIC AV"},{"Extensions":{"Distances":{"PresentableDistance":"8.2 miles away","DistanceFromCall":13248.39,"StopsFromCall":25,"CallDistanceAlongRoute":5956.33}},"StopPointRef":"MTA_303256","VisitNumber":1,"StopPointName":"LIVINGSTON ST/NEVINS ST"},{"Extensions":{"Distances":{"PresentableDistance":"8.4 miles away","DistanceFromCall":13506.38,"StopsFromCall":26,"CallDistanceAlongRoute":6214.32}},"StopPointRef":"MTA_306892","VisitNumber":1,"StopPointName":"LIVINGSTON ST/BOND ST"},{"Extensions":{"Distances":{"PresentableDistance":"8.5 miles away","DistanceFromCall":13705.97,"StopsFromCall":27,"CallDistanceAlongRoute":6413.91}},"StopPointRef":"MTA_303258","VisitNumber":1,"StopPointName":"LIVINGSTON ST/HOYT ST"},{"Extensions":{"Distances":{"PresentableDistance":"8.6 miles away","DistanceFromCall":13859.0,"StopsFromCall":28,"CallDistanceAlongRoute":6566.94}},"StopPointRef":"MTA_303259","VisitNumber":1,"StopPointName":"LIVINGSTON ST/SMITH ST"},{"Extensions":{"Distances":{"PresentableDistance":"8.9 miles away","DistanceFromCall":14282.89,"StopsFromCall":29,"CallDistanceAlongRoute":6990.83}},"StopPointRef":"MTA_302434","VisitNumber":1,"StopPointName":"JORALEMON ST/COURT ST"},{"Extensions":{"Distances":{"PresentableDistance":"9.0 miles away","DistanceFromCall":14446.69,"StopsFromCall":30,"CallDistanceAlongRoute":7154.63}},"StopPointRef":"MTA_801026","VisitNumber":1,"StopPointName":"LIVINGSTON ST/COURT ST"}]}},"RecordedAtTime":"2014-11-19T17:23:01.000-05:00"},{"MonitoredVehicleJourney":{"LineRef":"MTA NYCT_B45","DirectionRef":"1","FramedVehicleJourneyRef":{"DataFrameRef":"2014-11-19","DatedVehicleJourneyRef":"MTA NYCT_EN_D4-Weekday-SDon-110100_B45_9"},"JourneyPatternRef":"MTA_B450028","PublishedLineName":"B45","OperatorRef":"MTA NYCT","OriginRef":"MTA_303557","DestinationRef":"MTA_801026","DestinationName":"DNTWN BKLYN COURT ST","OriginAimedDepartureTime":"2014-11-19T17:18:00.000-05:00","SituationRef":[{"SituationSimpleRef":"MTA NYCT_76244"}],"Monitored":true,"VehicleLocation":{"Longitude":-73.987379,"Latitude":40.69027},"Bearing":338.90326,"ProgressRate":"normalProgress","ProgressStatus":"prevTrip","BlockRef":"MTA NYCT_EN_D4-Weekday-SDon_E_EN_51240_B45-9","VehicleRef":"MTA NYCT_6832","MonitoredCall":{"Extensions":{"Distances":{"PresentableDistance":"7.1 miles away","DistanceFromCall":11443.58,"StopsFromCall":49,"CallDistanceAlongRoute":3984.23}},"StopPointRef":"MTA_303574","VisitNumber":1,"StopPointName":"WASHINGTON AV/BERGEN ST"},"OnwardCalls":{"OnwardCall":[{"Extensions":{"Distances":{"PresentableDistance":"4.6 miles away","DistanceFromCall":7459.54,"StopsFromCall":0,"CallDistanceAlongRoute":0.2}},"StopPointRef":"MTA_303557","VisitNumber":1,"StopPointName":"ST JOHNS PL/RALPH AV"},{"Extensions":{"Distances":{"PresentableDistance":"4.8 miles away","DistanceFromCall":7693.13,"StopsFromCall":1,"CallDistanceAlongRoute":233.78}},"StopPointRef":"MTA_303558","VisitNumber":1,"StopPointName":"ST JOHNS PL/BUFFALO AV"},{"Extensions":{"Distances":{"PresentableDistance":"4.9 miles away","DistanceFromCall":7913.06,"StopsFromCall":2,"CallDistanceAlongRoute":453.72}},"StopPointRef":"MTA_306894","VisitNumber":1,"StopPointName":"ST JOHNS PL/ROCHESTER AV"},{"Extensions":{"Distances":{"PresentableDistance":"5.0 miles away","DistanceFromCall":8100.86,"StopsFromCall":3,"CallDistanceAlongRoute":641.51}},"StopPointRef":"MTA_303560","VisitNumber":1,"StopPointName":"ST JOHNS PL/UTICA AV"},{"Extensions":{"Distances":{"PresentableDistance":"5.2 miles away","DistanceFromCall":8380.19,"StopsFromCall":4,"CallDistanceAlongRoute":920.85}},"StopPointRef":"MTA_303561","VisitNumber":1,"StopPointName":"ST JOHNS PL/SCHENECTADY AV"},{"Extensions":{"Distances":{"PresentableDistance":"5.4 miles away","DistanceFromCall":8614.41,"StopsFromCall":5,"CallDistanceAlongRoute":1155.07}},"StopPointRef":"MTA_303562","VisitNumber":1,"StopPointName":"ST JOHNS PL/TROY AV"},{"Extensions":{"Distances":{"PresentableDistance":"5.5 miles away","DistanceFromCall":8848.54,"StopsFromCall":6,"CallDistanceAlongRoute":1389.19}},"StopPointRef":"MTA_303563","VisitNumber":1,"StopPointName":"ST JOHNS PL/ALBANY AV"},{"Extensions":{"Distances":{"PresentableDistance":"5.6 miles away","DistanceFromCall":9036.4,"StopsFromCall":7,"CallDistanceAlongRoute":1577.05}},"StopPointRef":"MTA_303564","VisitNumber":1,"StopPointName":"ST JOHNS PL/KINGSTON AV"},{"Extensions":{"Distances":{"PresentableDistance":"5.8 miles away","DistanceFromCall":9269.76,"StopsFromCall":8,"CallDistanceAlongRoute":1810.41}},"StopPointRef":"MTA_303565","VisitNumber":1,"StopPointName":"ST JOHNS PL/BROOKLYN AV"},{"Extensions":{"Distances":{"PresentableDistance":"5.9 miles away","DistanceFromCall":9507.7,"StopsFromCall":9,"CallDistanceAlongRoute":2048.36}},"StopPointRef":"MTA_303566","VisitNumber":1,"StopPointName":"ST JOHNS PL/NEW YORK AV"},{"Extensions":{"Distances":{"PresentableDistance":"6.1 miles away","DistanceFromCall":9739.68,"StopsFromCall":10,"CallDistanceAlongRoute":2280.33}},"StopPointRef":"MTA_303567","VisitNumber":1,"StopPointName":"ST JOHNS PL/NOSTRAND AV"},{"Extensions":{"Distances":{"PresentableDistance":"6.2 miles away","DistanceFromCall":9973.67,"StopsFromCall":11,"CallDistanceAlongRoute":2514.32}},"StopPointRef":"MTA_303568","VisitNumber":1,"StopPointName":"ST JOHNS PL/ROGERS AV"},{"Extensions":{"Distances":{"PresentableDistance":"6.4 miles away","DistanceFromCall":10231.48,"StopsFromCall":12,"CallDistanceAlongRoute":2772.13}},"StopPointRef":"MTA_303569","VisitNumber":1,"StopPointName":"STERLING PL/BEDFORD AV"},{"Extensions":{"Distances":{"PresentableDistance":"6.5 miles away","DistanceFromCall":10464.32,"StopsFromCall":13,"CallDistanceAlongRoute":3004.97}},"StopPointRef":"MTA_303570","VisitNumber":1,"StopPointName":"STERLING PL/FRANKLIN AV"},{"Extensions":{"Distances":{"PresentableDistance":"6.7 miles away","DistanceFromCall":10713.95,"StopsFromCall":14,"CallDistanceAlongRoute":3254.61}},"StopPointRef":"MTA_308021","VisitNumber":1,"StopPointName":"STERLING PL/CLASSON AV"},{"Extensions":{"Distances":{"PresentableDistance":"6.8 miles away","DistanceFromCall":10952.89,"StopsFromCall":15,"CallDistanceAlongRoute":3493.54}},"StopPointRef":"MTA_303572","VisitNumber":1,"StopPointName":"STERLING PL/WASHINGTON AV"},{"Extensions":{"Distances":{"PresentableDistance":"7.0 miles away","DistanceFromCall":11225.38,"StopsFromCall":16,"CallDistanceAlongRoute":3766.03}},"StopPointRef":"MTA_303573","VisitNumber":1,"StopPointName":"WASHINGTON AV/PROSPECT PL"},{"Extensions":{"Distances":{"PresentableDistance":"7.1 miles away","DistanceFromCall":11443.58,"StopsFromCall":17,"CallDistanceAlongRoute":3984.23}},"StopPointRef":"MTA_303574","VisitNumber":1,"StopPointName":"WASHINGTON AV/BERGEN ST"},{"Extensions":{"Distances":{"PresentableDistance":"7.2 miles away","DistanceFromCall":11631.21,"StopsFromCall":18,"CallDistanceAlongRoute":4171.86}},"StopPointRef":"MTA_303575","VisitNumber":1,"StopPointName":"WASHINGTON AV/PACIFIC ST"},{"Extensions":{"Distances":{"PresentableDistance":"7.3 miles away","DistanceFromCall":11746.98,"StopsFromCall":19,"CallDistanceAlongRoute":4287.63}},"StopPointRef":"MTA_306514","VisitNumber":1,"StopPointName":"ATLANTIC AV/WASHINGTON AV"},{"Extensions":{"Distances":{"PresentableDistance":"7.4 miles away","DistanceFromCall":11846.18,"StopsFromCall":20,"CallDistanceAlongRoute":4386.84}},"StopPointRef":"MTA_303576","VisitNumber":1,"StopPointName":"ATLANTIC AV/WAVERLY AV"},{"Extensions":{"Distances":{"PresentableDistance":"7.5 miles away","DistanceFromCall":12030.71,"StopsFromCall":21,"CallDistanceAlongRoute":4571.36}},"StopPointRef":"MTA_303577","VisitNumber":1,"StopPointName":"ATLANTIC AV/VANDERBILT AV"},{"Extensions":{"Distances":{"PresentableDistance":"7.6 miles away","DistanceFromCall":12304.3,"StopsFromCall":22,"CallDistanceAlongRoute":4844.95}},"StopPointRef":"MTA_303578","VisitNumber":1,"StopPointName":"ATLANTIC AV/CARLTON AV"},{"Extensions":{"Distances":{"PresentableDistance":"7.7 miles away","DistanceFromCall":12393.73,"StopsFromCall":23,"CallDistanceAlongRoute":4934.38}},"StopPointRef":"MTA_801175","VisitNumber":1,"StopPointName":"ATLANTIC AV/CUMBERLAND ST"},{"Extensions":{"Distances":{"PresentableDistance":"8.0 miles away","DistanceFromCall":12945.3,"StopsFromCall":24,"CallDistanceAlongRoute":5485.95}},"StopPointRef":"MTA_303254","VisitNumber":1,"StopPointName":"FLATBUSH AV/ATLANTIC AV"},{"Extensions":{"Distances":{"PresentableDistance":"8.3 miles away","DistanceFromCall":13415.68,"StopsFromCall":25,"CallDistanceAlongRoute":5956.33}},"StopPointRef":"MTA_303256","VisitNumber":1,"StopPointName":"LIVINGSTON ST/NEVINS ST"},{"Extensions":{"Distances":{"PresentableDistance":"8.5 miles away","DistanceFromCall":13673.67,"StopsFromCall":26,"CallDistanceAlongRoute":6214.32}},"StopPointRef":"MTA_306892","VisitNumber":1,"StopPointName":"LIVINGSTON ST/BOND ST"},{"Extensions":{"Distances":{"PresentableDistance":"8.6 miles away","DistanceFromCall":13873.26,"StopsFromCall":27,"CallDistanceAlongRoute":6413.91}},"StopPointRef":"MTA_303258","VisitNumber":1,"StopPointName":"LIVINGSTON ST/HOYT ST"},{"Extensions":{"Distances":{"PresentableDistance":"8.7 miles away","DistanceFromCall":14026.29,"StopsFromCall":28,"CallDistanceAlongRoute":6566.94}},"StopPointRef":"MTA_303259","VisitNumber":1,"StopPointName":"LIVINGSTON ST/SMITH ST"},{"Extensions":{"Distances":{"PresentableDistance":"9.0 miles away","DistanceFromCall":14450.18,"StopsFromCall":29,"CallDistanceAlongRoute":6990.83}},"StopPointRef":"MTA_302434","VisitNumber":1,"StopPointName":"JORALEMON ST/COURT ST"},{"Extensions":{"Distances":{"PresentableDistance":"9.1 miles away","DistanceFromCall":14613.98,"StopsFromCall":30,"CallDistanceAlongRoute":7154.63}},"StopPointRef":"MTA_801026","VisitNumber":1,"StopPointName":"LIVINGSTON ST/COURT ST"}]}},"RecordedAtTime":"2014-11-19T17:23:10.000-05:00"}],"ResponseTimestamp":"2014-11-19T17:23:26.316-05:00","ValidUntil":"2014-11-19T17:24:26.316-05:00"}],"SituationExchangeDelivery":[{"Situations":{"PtSituationElement":[{"PublicationWindow":{"StartTime":"2014-07-10T00:00:00.000-04:00","EndTime":"2014-12-31T23:59:00.000-05:00"},"Severity":"undefined","Summary":"B14, B15, B16, B17, B25, B35/B35","Description":"B14, B15, B16, B17, B25, B35/B35 LTD, B41/B41 LTD, B43, B44/B44 SBS and B45buses experiencing delays due to construction on the Gowanus Expy\nRush Hours, 7 AM to 9 AM and 4 PM to 7 PM, Mon to Fri, until further notice\n\n Please allow additional travel time.","Affects":{"VehicleJourneys":{"AffectedVehicleJourney":[{"LineRef":"MTA NYCT_B14","DirectionRef":"0"},{"LineRef":"MTA NYCT_B14","DirectionRef":"1"},{"LineRef":"MTA NYCT_B15","DirectionRef":"0"},{"LineRef":"MTA NYCT_B15","DirectionRef":"1"},{"LineRef":"MTA NYCT_B16","DirectionRef":"0"},{"LineRef":"MTA NYCT_B16","DirectionRef":"1"},{"LineRef":"MTA NYCT_B17","DirectionRef":"0"},{"LineRef":"MTA NYCT_B17","DirectionRef":"1"},{"LineRef":"MTA NYCT_B25","DirectionRef":"0"},{"LineRef":"MTA NYCT_B25","DirectionRef":"1"},{"LineRef":"MTA NYCT_B35","DirectionRef":"0"},{"LineRef":"MTA NYCT_B35","DirectionRef":"0"},{"LineRef":"MTA NYCT_B35","DirectionRef":"1"},{"LineRef":"MTA NYCT_B35","DirectionRef":"1"},{"LineRef":"MTA NYCT_B41","DirectionRef":"0"},{"LineRef":"MTA NYCT_B41","DirectionRef":"0"},{"LineRef":"MTA NYCT_B41","DirectionRef":"1"},{"LineRef":"MTA NYCT_B41","DirectionRef":"1"},{"LineRef":"MTA NYCT_B43","DirectionRef":"0"},{"LineRef":"MTA NYCT_B43","DirectionRef":"1"},{"LineRef":"MTA NYCT_B44","DirectionRef":"0"},{"LineRef":"MTA NYCT_B44","DirectionRef":"1"},{"LineRef":"MTA NYCT_B45","DirectionRef":"0"},{"LineRef":"MTA NYCT_B45","DirectionRef":"1"}]}},"Consequences":{"Consequence":[{"Condition":"altered"}]},"CreationTime":"2014-07-10T00:00:00.000-04:00","SituationNumber":"MTA NYCT_76244"}]}}]}}}